langgraph_agentflow/__init__.py
langgraph_agentflow/py.typed
langgraph_agentflow/multi_step/__init__.py
langgraph_agentflow/multi_step/agents.py
langgraph_agentflow/multi_step/graph.py
langgraph_agentflow/multi_step/prompts.py
langgraph_agentflow/multi_step/state.py
langgraph_agentflow/single_step/__init__.py
langgraph_agentflow/single_step/agent_factory.py
langgraph_agentflow/single_step/agent_types.py
langgraph_agentflow/single_step/graph_builder.py
langgraph_agentflow/single_step/interaction.py
langgraph_agentflow/single_step/router.py
langgraph_agentflow/single_step/specialized_agent.py
langgraph_agentflow/single_step/visualization.py
langgraph_agentflow-0.0.1.dist-info/licenses/LICENSE
tests/__init__.py
tests/test_integration.py
tests/multi_step/__init__.py
tests/multi_step/test_agents.py
tests/multi_step/test_graph.py
tests/multi_step/test_state.py
tests/single_step/__init__.py
tests/single_step/test_agent_factory.py
tests/single_step/test_graph_builder.py
tests/single_step/test_router.py
tests/single_step/test_specialized_agent.py
langgraph_agentflow-0.0.1.dist-info/METADATA
langgraph_agentflow-0.0.1.dist-info/WHEEL
langgraph_agentflow-0.0.1.dist-info/dependency_links.txt
langgraph_agentflow-0.0.1.dist-info/top_level.txt
langgraph_agentflow-0.0.1.dist-info/RECORD
