Metadata-Version: 2.4
Name: langgraph-agentflow
Version: 0.0.1
Summary: AgentFlow is a Python library that automates the orchestration of multi-step agent workflows by integrating intelligent planning, routing, and execution of specialized operations.
Home-page: https://github.com/KameniAlexNea/langgraph-agentflow
Author: Alex Kameni
Author-email: kamenialexnea@gmail.com
Classifier: Development Status :: 3 - Alpha
Classifier: Intended Audience :: Developers
Classifier: License :: OSI Approved :: MIT License
Classifier: Programming Language :: Python :: 3
Classifier: Programming Language :: Python :: 3.8
Classifier: Programming Language :: Python :: 3.9
Classifier: Programming Language :: Python :: 3.10
Classifier: Programming Language :: Python :: 3.11
Requires-Python: >=3.8
License-File: LICENSE
Requires-Dist: langgraph>=0.0.15
Requires-Dist: langchain-core>=0.1.0
Requires-Dist: loguru>=0.7.0
Requires-Dist: typing-extensions>=4.5.0
Provides-Extra: dev
Requires-Dist: pytest>=7.0.0; extra == "dev"
Requires-Dist: black>=23.0.0; extra == "dev"
Requires-Dist: isort>=5.0.0; extra == "dev"
Requires-Dist: mypy>=1.0.0; extra == "dev"
Provides-Extra: examples
Requires-Dist: langchain-ollama; extra == "examples"
Requires-Dist: pygraphviz; extra == "examples"
Requires-Dist: jupyter; extra == "examples"
Requires-Dist: pickleshare; extra == "examples"
Dynamic: author
Dynamic: author-email
Dynamic: classifier
Dynamic: description
Dynamic: description-content-type
Dynamic: home-page
Dynamic: license-file
Dynamic: provides-extra
Dynamic: requires-dist
Dynamic: requires-python
Dynamic: summary
